rtl/sevsegdis.v
module seven_segment_display (
  input [3:0] bcd_in,
  output reg [6:0] seg_out
);
  always @(*) begin
    case(bcd_in)
      4'b0000: seg_out = 7'b1111110;
      4'b0001: seg_out = 7'b0110000;
      4'b0010: seg_out = 7'b1101101;
      4'b0011: seg_out = 7'b1111001;
      4'b0100: seg_out = 7'b0110011;
      4'b0101: seg_out = 7'b1011011;
      4'b0110: seg_out = 7'b1011111;
      4'b0111: seg_out = 7'b1110000;
      4'b1000: seg_out = 7'b1111111;
      4'b1001: seg_out = 7'b1111011;
      default: seg_out = 7'b0000000;
    endcase
  end
endmodule

tb/sevenseg_tb.v
module seven_segment_display_tb;
  reg [3:0] bcd_in;
  wire [6:0] seg_out;

  seven_segment_display uut (
    .bcd_in(bcd_in),
    .seg_out(seg_out)
  );

  integer i;

  initial begin
    $dumpfile("seven_segment.vcd");
    $dumpvars(0, seven_segment_display_tb);
    $display("--------7segment display--------");
    $display("%Time\tBCD\tgfedcba");
    for (i = 0; i < 12; i = i + 1) begin
      bcd_in = i[3:0];
      #10;
      $display("%0t\t%d\t%b", $time, bcd_in, seg_out);
    end
    $finish;
  end
endmodule

sim/seven_segment.vcd
$date
	Thu Aug 20 20:09:05 2026
$end
$version
	Icarus Verilog
$end
$timescale
	1s
$end
$scope module seven_segment_display_tb $end
$var wire 7 ! seg_out [6:0] $end
$var reg 4 " bcd_in [3:0] $end
$var integer 32 # i [31:0] $end
$scope module uut $end
$var wire 4 $ bcd_in [3:0] $end
$var reg 7 % seg_out [6:0] $end
$upscope $end
$upscope $end
$enddefinitions $end
$comment Show the parameter values. $end
$dumpall
$end
#0
$dumpvars
b1111110 %
b0 $
b0 #
b0 "
b1111110 !
$end
#10
b110000 !
b110000 %
b1 "
b1 $
b1 #
#20
b1101101 !
b1101101 %
b10 "
b10 $
b10 #
#30
b1111001 !
b1111001 %
b11 "
b11 $
b11 #
#40
b110011 !
b110011 %
b100 "
b100 $
b100 #
#50
b1011011 !
b1011011 %
b101 "
b101 $
b101 #
#60
b1011111 !
b1011111 %
b110 "
b110 $
b110 #
#70
b1110000 !
b1110000 %
b111 "
b111 $
b111 #
#80
b1111111 !
b1111111 %
b1000 "
b1000 $
b1000 #
#90
b1111011 !
b1111011 %
b1001 "
b1001 $
b1001 #
#100
b0 !
b0 %
b1010 "
b1010 $
b1010 #
#110
b1011 "
b1011 $
b1011 #
#120
b1100 #
